{
    "$schema": "https://schema.management.azure.com/schemas/2015-01-01/deploymentParameters.json#",
    "contentVersion": "1.0.0.0",
  "parameters":
  {
    "administratorLogin":
    {
      "value": "myadmin"
    },
    "databaseName":
    {
      "value": "customers"
    },
    "location":
    {
      "value": "centralus"
    },
      "deployPackageFolder": {
          "value": "Resources"
      },
      "deployPackageFileName": {
          "value": "CustomersDB.bacpac"
      },
      "projectName": {
          "value": "DeployDataApplication"
      }
    
      
  }
}